nevermined_compute_api/__init__.py
nevermined_compute_api/argo-workflow.yaml
nevermined_compute_api/constants.py
nevermined_compute_api/log.py
nevermined_compute_api/myapp.py
nevermined_compute_api/routes.py
nevermined_compute_api/run.py
nevermined_compute_api/workflow_utils.py
nevermined_compute_api-0.3.0.dist-info/LICENSE
nevermined_compute_api-0.3.0.dist-info/METADATA
nevermined_compute_api-0.3.0.dist-info/NOTICE
nevermined_compute_api-0.3.0.dist-info/WHEEL
nevermined_compute_api-0.3.0.dist-info/top_level.txt
nevermined_compute_api-0.3.0.dist-info/RECORD
