Metadata-Version: 2.1
Name: nevermined-compute-api
Version: 0.3.0
Summary: Infrastructure Operator Micro-service
Home-page: https://github.com/nevermined-io/compute-api
Author: Keyko
Author-email: root@nevermined.io
License: Apache Software License 2.0
Keywords: nevermined-compute-api
Platform: UNKNOWN
Classifier: Development Status :: 2 - Pre-Alpha
Classifier: Intended Audience :: Developers
Classifier: License :: OSI Approved :: Apache Software License
Classifier: Natural Language :: English
Classifier: Programming Language :: Python :: 3.7
Requires-Dist: coloredlogs
Requires-Dist: Flask (==1.1.2)
Requires-Dist: Flask-Cors (==3.0.8)
Requires-Dist: flask-swagger (==0.2.14)
Requires-Dist: flask-swagger-ui (==3.20.9)
Requires-Dist: Jinja2 (>=2.10.1)
Requires-Dist: argo-workflows-fvdnabee
Requires-Dist: kubernetes (~=11.0)
Requires-Dist: requests (>=2.21.0)
Requires-Dist: gunicorn (==19.9.0)
Requires-Dist: PyYAML (==5.3)
Requires-Dist: pytz
Requires-Dist: web3 (==5.9.0)
Requires-Dist: nevermined-sdk-py (==0.9.0rc0)
Provides-Extra: dev
Requires-Dist: bumpversion ; extra == 'dev'
Requires-Dist: pkginfo ; extra == 'dev'
Requires-Dist: twine ; extra == 'dev'
Requires-Dist: watchdog ; extra == 'dev'
Requires-Dist: coverage ; extra == 'dev'
Requires-Dist: mccabe ; extra == 'dev'
Requires-Dist: pylint ; extra == 'dev'
Requires-Dist: pytest ; extra == 'dev'
Requires-Dist: pytest-mock (==3.2.0) ; extra == 'dev'
Provides-Extra: test
Requires-Dist: coverage ; extra == 'test'
Requires-Dist: mccabe ; extra == 'test'
Requires-Dist: pylint ; extra == 'test'
Requires-Dist: pytest ; extra == 'test'
Requires-Dist: pytest-mock (==3.2.0) ; extra == 'test'
